ExcelToCsv/ExcelToCsv.py
ExcelToCsv/__init__.py
ExcelToCsv-0.1.1.dist-info/DESCRIPTION.rst
ExcelToCsv-0.1.1.dist-info/METADATA
ExcelToCsv-0.1.1.dist-info/RECORD
ExcelToCsv-0.1.1.dist-info/WHEEL
ExcelToCsv-0.1.1.dist-info/entry_points.txt
ExcelToCsv-0.1.1.dist-info/metadata.json
ExcelToCsv-0.1.1.dist-info/top_level.txt
