Metadata-Version: 2.0
Name: ExcelToCsv
Version: 0.1.1
Summary: A python package to convert excel spreadsheets to csv files
Home-page: https://github.com/WaylonWalker/ExcelToCsv
Author: Waylon Walker
Author-email: quadmx08@gmail.com
License: MIT
Platform: UNKNOWN
Classifier: Development Status :: 3 - Alpha
Classifier: Topic :: Utilities
Requires-Dist: xlrd
